.travis.yml
AUTHORS
ChangeLog
LICENSE
README.rst
requirements-test.txt
requirements.txt
setup.cfg
setup.py
mgmtsystem/__init__.py
mgmtsystem/azure.py
mgmtsystem/base.py
mgmtsystem/ec2.py
mgmtsystem/exceptions.py
mgmtsystem/google.py
mgmtsystem/hawkular.py
mgmtsystem/kubernetes.py
mgmtsystem/openshift.py
mgmtsystem/openstack.py
mgmtsystem/openstack_infra.py
mgmtsystem/rest_client.py
mgmtsystem/rhevm.py
mgmtsystem/scvmm.py
mgmtsystem/virtualcenter.py
mgmtsystem/websocket_client.py
mgmtsystem.egg-info/PKG-INFO
mgmtsystem.egg-info/SOURCES.txt
mgmtsystem.egg-info/dependency_links.txt
mgmtsystem.egg-info/not-zip-safe
mgmtsystem.egg-info/pbr.json
mgmtsystem.egg-info/requires.txt
mgmtsystem.egg-info/top_level.txt
mgmtsystem/utils/__init__.py
tests/__init__.py
tests/test_hawkular.py
tests/test_openstack.py
tests/resources/hawkular/alerts/events.json
tests/resources/hawkular/inventory/feeds.json
tests/resources/hawkular/inventory/status.json
tests/resources/hawkular/inventory/feeds/328c17e1-c97f-4583-89d8-73feb0cf47f6/resourceTypes.json
tests/resources/hawkular/inventory/feeds/328c17e1-c97f-4583-89d8-73feb0cf47f6/resourceTypes/Datasource/resources.json
tests/resources/hawkular/inventory/feeds/328c17e1-c97f-4583-89d8-73feb0cf47f6/resourceTypes/Deployment/resources.json
tests/resources/hawkular/inventory/feeds/328c17e1-c97f-4583-89d8-73feb0cf47f6/resourceTypes/Domain WildFly Server/resources.json
tests/resources/hawkular/inventory/feeds/328c17e1-c97f-4583-89d8-73feb0cf47f6/resourceTypes/Host Controller/resources.json
tests/resources/hawkular/inventory/feeds/328c17e1-c97f-4583-89d8-73feb0cf47f6/resourceTypes/JMS Queue/resources.json
tests/resources/hawkular/inventory/feeds/328c17e1-c97f-4583-89d8-73feb0cf47f6/resourceTypes/JMS Topic/resources.json
tests/resources/hawkular/inventory/feeds/328c17e1-c97f-4583-89d8-73feb0cf47f6/resourceTypes/SubDeployment/resources.json
tests/resources/hawkular/inventory/feeds/328c17e1-c97f-4583-89d8-73feb0cf47f6/resourceTypes/WildFly Server/resources.json
tests/resources/hawkular/inventory/feeds/328c17e1-c97f-4583-89d8-73feb0cf47f6/resourceTypes/XA Datasource/resources.json
