Metadata-Version: 1.1
Name: mgmtsystem
Version: 1.5.4
Summary: A base system for provider management
Home-page: UNKNOWN
Author: Peter Savage
Author-email: psavage@redhat.com
License: UNKNOWN
Keywords: setup
Platform: UNKNOWN
Classifier: Development Status :: 4 - Beta
Classifier: Environment :: Console
Classifier: Intended Audience :: Developers
Classifier: Operating System :: OS Independent
Classifier: Programming Language :: Python :: 2
Classifier: Programming Language :: Python :: 2.7
Classifier: Topic :: Utilities
